{"meta": {"fund_house": "ICICI Prudential Mutual Fund", "scheme_type": "Open Ended Schemes", "scheme_category": "Debt Scheme - Gilt Fund", "scheme_code": 100369, "scheme_name": "ICICI Prudential Gilt Fund - Growth"}, "data": [{"date": "15-09-2020", "nav": "75.84600"}, {"date": "15-07-2020", "nav": "76.33860"}, {"date": "15-06-2020", "nav": "75.34190"}, {"date": "15-05-2020", "nav": "74.04500"}, {"date": "15-04-2020", "nav": "71.09550"}, {"date": "15-01-2020", "nav": "68.86870"}, {"date": "15-11-2019", "nav": "68.12960"}, {"date": "15-10-2019", "nav": "67.78690"}, {"date": "15-07-2019", "nav": "67.68760"}, {"date": "15-05-2019", "nav": "63.94970"}, {"date": "15-04-2019", "nav": "63.52090"}, {"date": "15-03-2019", "nav": "63.13130"}, {"date": "15-02-2019", "nav": "62.60300"}, {"date": "15-01-2019", "nav": "62.50860"}, {"date": "15-11-2018", "nav": "61.27300"}, {"date": "15-10-2018", "nav": "60.90540"}, {"date": "15-06-2018", "nav": "59.33960"}, {"date": "15-05-2018", "nav": "58.88810"}, {"date": "15-03-2018", "nav": "58.21380"}, {"date": "15-02-2018", "nav": "57.97270"}, {"date": "15-01-2018", "nav": "58.37000"}, {"date": "15-12-2017", "nav": "58.94520"}, {"date": "15-11-2017", "nav": "59.02530"}, {"date": "15-09-2017", "nav": "59.91330"}, {"date": "15-06-2017", "nav": "59.65530"}, {"date": "15-05-2017", "nav": "56.97500"}, {"date": "15-03-2017", "nav": "55.58070"}, {"date": "15-02-2017", "nav": "55.96560"}, {"date": "15-12-2016", "nav": "57.37090"}, {"date": "15-11-2016", "nav": "57.06920"}, {"date": "15-09-2016", "nav": "54.98320"}, {"date": "15-07-2016", "nav": "52.80950"}, {"date": "15-06-2016", "nav": "51.10470"}, {"date": "15-03-2016", "nav": "48.87160"}, {"date": "15-02-2016", "nav": "47.92500"}, {"date": "15-01-2016", "nav": "48.13340"}, {"date": "15-12-2015", "nav": "48.52140"}, {"date": "15-10-2015", "nav": "49.09390"}, {"date": "15-09-2015", "nav": "47.96420"}, {"date": "15-07-2015", "nav": "46.84260"}, {"date": "15-06-2015", "nav": "46.19050"}, {"date": "15-05-2015", "nav": "46.67410"}, {"date": "15-04-2015", "nav": "47.20680"}, {"date": "15-01-2015", "nav": "46.63740"}]}