{"meta": {"fund_house": "UTI Mutual Fund", "scheme_type": "Open Ended Schemes", "scheme_category": "Equity Scheme - Sectoral/ Thematic", "scheme_code": 100807, "scheme_name": "UTI Healthcare Fund - Regular Plan - Growth Option"}, "data": [{"date": "15-09-2020", "nav": "126.05940"}, {"date": "15-07-2020", "nav": "107.51570"}, {"date": "15-06-2020", "nav": "105.37510"}, {"date": "15-05-2020", "nav": "98.66120"}, {"date": "15-04-2020", "nav": "96.90850"}, {"date": "15-01-2020", "nav": "87.65250"}, {"date": "15-11-2019", "nav": "81.10810"}, {"date": "15-10-2019", "nav": "77.37490"}, {"date": "15-07-2019", "nav": "79.19030"}, {"date": "15-05-2019", "nav": "80.59830"}, {"date": "15-04-2019", "nav": "86.26990"}, {"date": "15-03-2019", "nav": "84.97470"}, {"date": "15-02-2019", "nav": "81.32210"}, {"date": "15-01-2019", "nav": "85.21520"}, {"date": "15-11-2018", "nav": "84.54490"}, {"date": "15-10-2018", "nav": "87.22390"}, {"date": "15-06-2018", "nav": "84.66050"}, {"date": "15-05-2018", "nav": "82.08190"}, {"date": "15-03-2018", "nav": "85.52670"}, {"date": "15-02-2018", "nav": "88.17300"}, {"date": "15-01-2018", "nav": "91.02640"}, {"date": "15-12-2017", "nav": "86.91530"}, {"date": "15-11-2017", "nav": "83.67670"}, {"date": "15-09-2017", "nav": "83.14910"}, {"date": "15-06-2017", "nav": "83.96460"}, {"date": "15-05-2017", "nav": "86.79460"}, {"date": "15-03-2017", "nav": "89.31490"}, {"date": "15-02-2017", "nav": "85.20950"}, {"date": "15-12-2016", "nav": "87.97780"}, {"date": "15-11-2016", "nav": "88.29850"}, {"date": "15-09-2016", "nav": "94.93970"}, {"date": "15-07-2016", "nav": "92.00740"}, {"date": "15-06-2016", "nav": "86.81470"}, {"date": "15-03-2016", "nav": "87.98770"}, {"date": "15-02-2016", "nav": "87.89070"}, {"date": "15-01-2016", "nav": "89.40940"}, {"date": "15-12-2015", "nav": "92.33360"}, {"date": "15-10-2015", "nav": "101.41560"}, {"date": "15-09-2015", "nav": "96.97810"}, {"date": "15-07-2015", "nav": "98.80360"}, {"date": "15-06-2015", "nav": "89.18240"}, {"date": "15-05-2015", "nav": "94.03590"}, {"date": "15-04-2015", "nav": "103.29770"}, {"date": "15-01-2015", "nav": "84.13260"}]}