{"meta": {"fund_house": "Sundaram Mutual Fund", "scheme_type": "Open Ended Schemes", "scheme_category": "Debt Scheme - Low Duration Fund", "scheme_code": 105564, "scheme_name": "Sundaram Low Duration Fund Retail Growth"}, "data": [{"date": "15-09-2020", "nav": "23.10070"}, {"date": "15-07-2020", "nav": "22.99990"}, {"date": "15-06-2020", "nav": "22.75690"}, {"date": "15-05-2020", "nav": "22.59060"}, {"date": "15-04-2020", "nav": "22.37040"}, {"date": "15-01-2020", "nav": "22.11480"}, {"date": "15-11-2019", "nav": "21.90200"}, {"date": "15-10-2019", "nav": "21.74630"}, {"date": "15-07-2019", "nav": "22.27980"}, {"date": "15-05-2019", "nav": "23.22160"}, {"date": "15-04-2019", "nav": "23.13130"}, {"date": "15-03-2019", "nav": "22.98060"}, {"date": "15-02-2019", "nav": "22.82610"}, {"date": "15-01-2019", "nav": "22.69830"}, {"date": "15-11-2018", "nav": "22.34480"}, {"date": "15-10-2018", "nav": "22.19880"}, {"date": "15-06-2018", "nav": "21.72510"}, {"date": "15-05-2018", "nav": "21.60290"}, {"date": "15-03-2018", "nav": "21.41040"}, {"date": "15-02-2018", "nav": "21.28960"}, {"date": "15-01-2018", "nav": "21.18570"}, {"date": "15-12-2017", "nav": "21.09190"}, {"date": "15-11-2017", "nav": "21.00510"}, {"date": "15-09-2017", "nav": "20.81170"}, {"date": "15-06-2017", "nav": "20.46210"}, {"date": "15-05-2017", "nav": "20.32790"}, {"date": "15-03-2017", "nav": "20.09410"}, {"date": "15-02-2017", "nav": "20.01000"}, {"date": "15-12-2016", "nav": "19.78500"}, {"date": "15-11-2016", "nav": "19.71840"}, {"date": "15-09-2016", "nav": "19.48770"}, {"date": "15-07-2016", "nav": "19.27240"}, {"date": "15-06-2016", "nav": "19.13610"}, {"date": "15-03-2016", "nav": "18.76190"}, {"date": "15-02-2016", "nav": "18.65100"}, {"date": "15-01-2016", "nav": "18.56210"}, {"date": "15-12-2015", "nav": "18.46520"}, {"date": "15-10-2015", "nav": "18.30300"}, {"date": "15-09-2015", "nav": "18.17540"}, {"date": "15-07-2015", "nav": "17.99380"}, {"date": "15-06-2015", "nav": "17.88070"}, {"date": "15-05-2015", "nav": "17.76620"}, {"date": "15-04-2015", "nav": "17.67920"}, {"date": "15-01-2015", "nav": "17.34130"}]}